amazon_photos/__init__.py
amazon_photos/__version__.py
amazon_photos/_api.py
amazon_photos/_constants.py
amazon_photos/_helpers.py
amazon_photos-0.0.97.dist-info/LICENSE
amazon_photos-0.0.97.dist-info/METADATA
amazon_photos-0.0.97.dist-info/WHEEL
amazon_photos-0.0.97.dist-info/top_level.txt
amazon_photos-0.0.97.dist-info/RECORD
