Metadata-Version: 2.1
Name: amazon-photos
Version: 0.0.97
Summary: Amazon Photos API
Home-page: https://github.com/trevorhobenshield/amazon_photos
Author: Trevor Hobenshield
Author-email: trevorhobenshield@gmail.com
License: MIT
Keywords: amazon photos api async search automation
Classifier: Environment :: Web Environment
Classifier: Intended Audience :: Developers
Classifier: Natural Language :: English
Classifier: Operating System :: Unix
Classifier: Operating System :: MacOS :: MacOS X
Classifier: Operating System :: Microsoft :: Windows
Classifier: Programming Language :: Python
Classifier: Programming Language :: Python :: 3
Classifier: Programming Language :: Python :: 3.10
Classifier: Programming Language :: Python :: 3.11
Classifier: Programming Language :: Python :: 3.12
Classifier: Topic :: Internet :: WWW/HTTP
Classifier: Topic :: Software Development :: Libraries
Classifier: Topic :: Software Development :: Libraries :: Python Modules
Requires-Python: >=3.10.10
License-File: LICENSE
Requires-Dist: psutil
Requires-Dist: nest-asyncio
Requires-Dist: tqdm
Requires-Dist: aiofiles
Requires-Dist: orjson
Requires-Dist: httpx[http2]
Requires-Dist: pandas
Requires-Dist: uvloop ; platform_system != "Windows"
Provides-Extra: extras
Requires-Dist: torch ; extra == 'extras'
Requires-Dist: torchvision ; extra == 'extras'
Requires-Dist: timm ; extra == 'extras'
Requires-Dist: Pillow ; extra == 'extras'
